pinkfish/__init__.py
pinkfish/analysis.py
pinkfish/benchmark.py
pinkfish/fetch.py
pinkfish/indicator.py
pinkfish/itable.py
pinkfish/pfcalendar.py
pinkfish/pfstatistics.py
pinkfish/plot.py
pinkfish/portfolio.py
pinkfish/stock_market_calendar.py
pinkfish/trade.py
pinkfish/utility.py
pinkfish-2.1.2.data/data/requirements.txt
pinkfish-2.1.2.dist-info/LICENSE
pinkfish-2.1.2.dist-info/METADATA
pinkfish-2.1.2.dist-info/WHEEL
pinkfish-2.1.2.dist-info/top_level.txt
pinkfish-2.1.2.dist-info/RECORD
